{
  "scenario_id": "es_short",
  "scenario_name": "Spanish Short",
  "status": "success",
  "result": {
    "job_id": "20251107_035258_69f6cff6",
    "status": "completed",
    "message": "Video generated successfully",
    "video_url": "/api/v1/videos/20251107_035258_69f6cff6_video.mp4",
    "metadata": {
      "duration_ms": 99721.66900000001,
      "tts_ms": 99605.31783103943,
      "avatar_ms": 115.98038673400879,
      "language": "es",
      "audio_duration_s": 3.6173333333333333
    }
  },
  "metrics": {
    "tts_ms": 99605.31783103943,
    "avatar_render_ms": 115.98038673400879,
    "total_generation_ms": 99721.66900000001,
    "audio_duration_s": 3.6173333333333333,
    "language_expected": "es",
    "language_detected": "ca",
    "language_from_text": "ca",
    "language_correctness_1_1": 0,
    "speaker_similarity": 0.0,
    "f0_rmse_hz": 0.0,
    "lip_sync_coherence_0_1": 0.0,
    "evaluator_total_time_s": 99.73802185058594
  },
  "video_path": "./outputs/es_short_20251107_035258_69f6cff6.mp4"
}